MANIFEST.in
README.txt
bootstrap.py
buildout.cfg
get.py
setup.py
src/zc/__init__.py
src/zc.buildoutsftp.egg-info/PKG-INFO
src/zc.buildoutsftp.egg-info/SOURCES.txt
src/zc.buildoutsftp.egg-info/dependency_links.txt
src/zc.buildoutsftp.egg-info/entry_points.txt
src/zc.buildoutsftp.egg-info/namespace_packages.txt
src/zc.buildoutsftp.egg-info/not-zip-safe
src/zc.buildoutsftp.egg-info/requires.txt
src/zc.buildoutsftp.egg-info/top_level.txt
src/zc/buildoutsftp/__init__.py
src/zc/buildoutsftp/main.test
src/zc/buildoutsftp/tests.py