Metadata-Version: 1.0
Name: zc.buildoutsftp
Version: 0.11.0
Summary: Specialized zc.buildout plugin to add sftp support.
Home-page: http://www.python.org/pypi/zc.buildoutsftp
Author: Jim Fulton
Author-email: jim@zope.com
License: ZPL 2.1
Keywords: buildout
Platform: UNKNOWN
Classifier: Framework :: Buildout
Classifier: Development Status :: 3 - Alpha
Classifier: Intended Audience :: Developers
Classifier: License :: OSI Approved :: Zope Public License
Classifier: Topic :: Software Development :: Build Tools
Classifier: Topic :: Software Development :: Libraries :: Python Modules
